{".FVER":1,".DATE_CREATED":1644801568980,".T":145592,".FILE_VERSION":77,".BIRTH_SESSION":"azxt5fnaua3h4r07zd80qi4p48y4smkxywl093bitsachu6w5nc8m35sv4jyb4b4",".LIST":{"ih53gjvywlpen8sw":{".NAME":"GUIElement",".CLASS":"App"}},".OID":"n87942o71ipdybu4",".ORIGINAL_FILE_SIZE":6545,".CREATOR":"8uqi0rivp58tr183",".MIME":"text/javascript; charset=utf-8",".NAME":"ImageView","Assets":"{\"GUIElement\":{\"id\":\"ih53gjvywlpen8sw\",\"type\":\"App\"}}",".CLASS":"App",".DATE_MODIFIED":1652359809142,".FILE_ENCODING":"ds1_1",".VERSION":80,".VERSHIST":0},{".FILE_VERSION":78,".T":163812,".FILE_ENCODING":"ds1_1",".ORIGINAL_FILE_SIZE":6550,".MIME":"text/javascript; charset=utf-8"},{".FILE_VERSION":79,".T":505216,".FILE_ENCODING":"ds1_1",".ORIGINAL_FILE_SIZE":6569,".MIME":"text/javascript; charset=utf-8"},{".FILE_VERSION":80,".T":9899,".FILE_ENCODING":"ds1_1",".ORIGINAL_FILE_SIZE":6568,".MIME":"text/javascript; charset=utf-8"},{".FILE_VERSION":81,".T":52538,".FILE_ENCODING":"ds1_1",".ORIGINAL_FILE_SIZE":6579,".MIME":"text/javascript; charset=utf-8"},{".FILE_VERSION":82,".T":169234,".FILE_ENCODING":"ds1_1",".ORIGINAL_FILE_SIZE":6601,".MIME":"text/javascript; charset=utf-8"},{".FILE_VERSION":83,".T":447117,".FILE_ENCODING":"ds1_1",".ORIGINAL_FILE_SIZE":6806,".MIME":"text/javascript; charset=utf-8"},{".FILE_VERSION":84,".T":24823,".FILE_ENCODING":"ds1_1",".ORIGINAL_FILE_SIZE":6910,".MIME":"text/javascript; charset=utf-8"},{".FILE_VERSION":85,".T":27331,".FILE_ENCODING":"ds1_1",".ORIGINAL_FILE_SIZE":6908,".MIME":"text/javascript; charset=utf-8"},{".FILE_VERSION":86,".T":158000,".FILE_ENCODING":"ds1_1",".ORIGINAL_FILE_SIZE":6884,".MIME":"text/javascript; charset=utf-8"},{".FILE_VERSION":87,".T":173517,".FILE_ENCODING":"ds1_1",".ORIGINAL_FILE_SIZE":6838,".MIME":"text/javascript; charset=utf-8"},{".FILE_VERSION":88,".T":37015,".FILE_ENCODING":"ds1_1",".ORIGINAL_FILE_SIZE":6691,".MIME":"text/javascript; charset=utf-8"},{".FILE_VERSION":89,".T":167632,".FILE_ENCODING":"ds1_1",".ORIGINAL_FILE_SIZE":6629,".MIME":"text/javascript; charset=utf-8"},{".FILE_VERSION":90,".T":234774,".FILE_ENCODING":"ds1_1",".ORIGINAL_FILE_SIZE":6683,".MIME":"text/javascript; charset=utf-8"},{".FILE_VERSION":91,".T":3581985,".FILE_ENCODING":"ds1_1",".ORIGINAL_FILE_SIZE":6713,".MIME":"text/javascript; charset=utf-8"},{".FILE_VERSION":92,".T":67035,".FILE_ENCODING":"ds1_1",".ORIGINAL_FILE_SIZE":6730,".MIME":"text/javascript; charset=utf-8"},{".FILE_VERSION":93,".T":122387,".FILE_ENCODING":"ds1_1",".ORIGINAL_FILE_SIZE":6749,".MIME":"text/javascript; charset=utf-8"},{".FILE_VERSION":94,".T":1671889,".FILE_ENCODING":"ds1_1",".ORIGINAL_FILE_SIZE":6684,".MIME":"text/javascript; charset=utf-8"},{".FILE_VERSION":95,".T":498891,".FILE_ENCODING":"ds1_1",".ORIGINAL_FILE_SIZE":6784,".MIME":"text/javascript; charset=utf-8"},{".FILE_VERSION":96,".T":2262522,".FILE_ENCODING":"ds1_1",".ORIGINAL_FILE_SIZE":6940,".MIME":"text/javascript; charset=utf-8"},{".FILE_VERSION":97,".T":169991339,".FILE_ENCODING":"ds1_1",".ORIGINAL_FILE_SIZE":7087,".MIME":"text/javascript; charset=utf-8"}